barry/__init__.py
barry/barplot.py
barry-0.0.1.dist-info/LICENSE
barry-0.0.1.dist-info/METADATA
barry-0.0.1.dist-info/WHEEL
barry-0.0.1.dist-info/top_level.txt
barry-0.0.1.dist-info/RECORD
