Metadata-Version: 2.1
Name: barry
Version: 0.0.1
Summary: Bar plots in terminal window
Home-page: https://github.com/fabianzoepf/barry
Author: Fabian Zoepf
Author-email: zoepf.fabian@gmail.com
License: UNKNOWN
Platform: UNKNOWN
Classifier: Programming Language :: Python :: 3
Classifier: License :: OSI Approved :: MIT License
Classifier: Operating System :: OS Independent
Requires-Python: >=3.5
